gemini_mcp/__init__.py
gemini_mcp/server.py
gemini_mcp/config/__init__.py
gemini_mcp/config/settings.py
gemini_mcp/middleware/__init__.py
gemini_mcp/middleware/error_handling.py
gemini_mcp/middleware/logging.py
gemini_mcp/services/__init__.py
gemini_mcp/services/gemini_client.py
gemini_mcp/tools/__init__.py
gemini_mcp/tools/gemini_tools.py
gemini_cli_mcp_tool-0.2.1.dist-info/METADATA
gemini_cli_mcp_tool-0.2.1.dist-info/WHEEL
gemini_cli_mcp_tool-0.2.1.dist-info/entry_points.txt
gemini_cli_mcp_tool-0.2.1.dist-info/licenses/LICENSE
gemini_cli_mcp_tool-0.2.1.dist-info/RECORD
