Metadata-Version: 2.4
Name: gemini-cli-mcp-tool
Version: 0.2.1
Summary: MCP server that wraps Gemini CLI for token-efficient AI operations
Project-URL: Homepage, https://github.com/mgiovani/gemini-cli-mcp-tool
Project-URL: Repository, https://github.com/mgiovani/gemini-cli-mcp-tool
Author-email: Giovani Moutinho <e@giovani.dev>
License: MIT
License-File: LICENSE
Keywords: ai,gemini,llm,mcp,model-context-protocol
Classifier: Development Status :: 3 - Alpha
Classifier: Intended Audience :: Developers
Classifier: License :: OSI Approved :: MIT License
Classifier: Programming Language :: Python :: 3
Classifier: Programming Language :: Python :: 3.12
Classifier: Programming Language :: Python :: 3.13
Classifier: Topic :: Software Development :: Libraries :: Python Modules
Requires-Python: >=3.12
Requires-Dist: anyio>=4.0.0
Requires-Dist: fastmcp>=2.11.0
Requires-Dist: pydantic-settings>=2.1.0
Requires-Dist: pydantic>=2.5.0
Requires-Dist: python-dotenv>=1.0.0
Requires-Dist: rich>=13.7.0
Requires-Dist: structlog>=23.2.0
